qav/__init__.py
qav/filters.py
qav/listpack.py
qav/py.typed
qav/questions.py
qav/utils.py
qav/validators.py
qav-1.1.9.dist-info/LICENSE
qav-1.1.9.dist-info/METADATA
qav-1.1.9.dist-info/WHEEL
qav-1.1.9.dist-info/top_level.txt
qav-1.1.9.dist-info/RECORD
