Metadata-Version: 2.1
Name: qav
Version: 1.1.9
Summary: Question Answer Validation
Home-page: https://github.com/UMIACS/qav
Author: Derek Yarnell
Author-email: derek@umiacs.umd.edu
Maintainer: UMIACS Staff
Maintainer-email: github@umiacs.umd.edu
License: LGPL v2.1
Platform: UNKNOWN
Classifier: Development Status :: 5 - Production/Stable
Classifier: Environment :: Console
Classifier: Intended Audience :: Developers
Classifier: License :: OSI Approved :: GNU Lesser General Public License v2 (LGPLv2)
Classifier: Natural Language :: English
Classifier: Operating System :: OS Independent
Classifier: Topic :: Software Development :: Libraries
Classifier: Programming Language :: Python :: 3
Classifier: Programming Language :: Python :: 3.6
License-File: LICENSE
Requires-Dist: netaddr
